{
  "components": [
    {
      "selector": "button",
      "type": "button",
      "text": "Commander Dashboard",
      "attributes": {},
      "isClickable": true,
      "isVisible": true,
      "coordinates": [
        809,
        141.39844131469727
      ]
    },
    {
      "selector": "button",
      "type": "button",
      "text": "Live Map",
      "attributes": {},
      "isClickable": true,
      "isVisible": true,
      "coordinates": [
        1111,
        141.3984375
      ]
    },
    {
      "selector": ".ios-button",
      "type": "button",
      "text": "Operations",
      "attributes": {},
      "isClickable": true,
      "isVisible": true,
      "coordinates": [
        467.84375,
        290.3984375
      ]
    },
    {
      "selector": ".ios-button",
      "type": "button",
      "text": "Conditions",
      "attributes": {},
      "isClickable": true,
      "isVisible": true,
      "coordinates": [
        467.41015625,
        328.3984375
      ]
    },
    {
      "selector": ".ios-button",
      "type": "button",
      "text": "Assets",
      "attributes": {},
      "isClickable": true,
      "isVisible": true,
      "coordinates": [
        453.1484375,
        366.3984375
      ]
    },
    {
      "selector": ".ios-button",
      "type": "button",
      "text": "AIP Commander",
      "attributes": {},
      "isClickable": true,
      "isVisible": true,
      "coordinates": [
        486.234375,
        404.3984375
      ]
    },
    {
      "selector": "#root",
      "type": "div",
      "text": "Command CenterCentralized emergency response command and controlCommander DashboardLive MapCommander DashboardCommand center for emergency response operations with real-time situational awarenessOperationsConditionsAssetsAIP CommanderZone AIMMEDIATETotal Buildings:150Population:1500Evacuated (120)In Progress (20)Refused (5)No Contact (3)Unchecked (2)Est. Completion: 5:35:07 PM2 units assignedZone BWARNINGTotal Buildings:75Population:2200Evacuated (60)In Progress (10)Refused (2)No Contact (2)Unchecked (1)Est. Completion: 7:35:07 PM1 units assignedZone CSTANDBYTotal Buildings:50Population:800Evacuated (40)In Progress (5)Refused (1)No Contact (1)Unchecked (1)Est. Completion: 9:35:07 PM1 units assignedEmergency Response System v1.0.0Powered by Mapbox & React • Real-time disaster monitoring",
      "attributes": {},
      "isClickable": false,
      "isVisible": true,
      "coordinates": [
        960,
        498.94921875
      ]
    },
    {
      "selector": ".evacuation-dashboard",
      "type": "div",
      "text": "Commander DashboardCommand center for emergency response operations with real-time situational awarenessOperationsConditionsAssetsAIP CommanderZone AIMMEDIATETotal Buildings:150Population:1500Evacuated (120)In Progress (20)Refused (5)No Contact (3)Unchecked (2)Est. Completion: 5:35:07 PM2 units assignedZone BWARNINGTotal Buildings:75Population:2200Evacuated (60)In Progress (10)Refused (2)No Contact (2)Unchecked (1)Est. Completion: 7:35:07 PM1 units assignedZone CSTANDBYTotal Buildings:50Population:800Evacuated (40)In Progress (5)Refused (1)No Contact (1)Unchecked (1)Est. Completion: 9:35:07 PM1 units assigned",
      "attributes": {},
      "isClickable": false,
      "isVisible": true,
      "coordinates": [
        960,
        581.8984375
      ]
    },
    {
      "selector": ".ios-card",
      "type": "div",
      "text": "Commander DashboardCommand center for emergency response operations with real-time situational awareness",
      "attributes": {},
      "isClickable": false,
      "isVisible": true,
      "coordinates": [
        960,
        237.8984375
      ]
    },
    {
      "selector": ".ios-container",
      "type": "div",
      "text": "Commander DashboardCommand center for emergency response operations with real-time situational awareness",
      "attributes": {},
      "isClickable": false,
      "isVisible": true,
      "coordinates": [
        960,
        237.8984375
      ]
    },
    {
      "selector": ".ios-flex-between",
      "type": "div",
      "text": "Commander DashboardCommand center for emergency response operations with real-time situational awareness",
      "attributes": {},
      "isClickable": false,
      "isVisible": true,
      "coordinates": [
        960,
        237.8984375
      ]
    },
    {
      "selector": ".ios-headline",
      "type": "h1",
      "text": "Commander Dashboard",
      "attributes": {},
      "isClickable": false,
      "isVisible": true,
      "coordinates": [
        960,
        228.3984375
      ]
    },
    {
      "selector": ".ios-caption",
      "type": "p",
      "text": "Command center for emergency response operations with real-time situational awareness",
      "attributes": {},
      "isClickable": false,
      "isVisible": true,
      "coordinates": [
        960,
        256.8984375
      ]
    },
    {
      "selector": ".ios-card",
      "type": "div",
      "text": "OperationsConditionsAssetsAIP Commander",
      "attributes": {},
      "isClickable": false,
      "isVisible": true,
      "coordinates": [
        960,
        347.3984375
      ]
    },
    {
      "selector": ".ios-container",
      "type": "div",
      "text": "OperationsConditionsAssetsAIP Commander",
      "attributes": {},
      "isClickable": false,
      "isVisible": true,
      "coordinates": [
        960,
        347.3984375
      ]
    },
    {
      "selector": ".ios-flex",
      "type": "div",
      "text": "OperationsConditionsAssetsAIP Commander",
      "attributes": {},
      "isClickable": false,
      "isVisible": true,
      "coordinates": [
        709,
        347.3984375
      ]
    },
    {
      "selector": ".ios-button",
      "type": "button",
      "text": "Operations",
      "attributes": {},
      "isClickable": true,
      "isVisible": true,
      "coordinates": [
        467.84375,
        290.3984375
      ]
    },
    {
      "selector": ".ios-button",
      "type": "button",
      "text": "Conditions",
      "attributes": {},
      "isClickable": true,
      "isVisible": true,
      "coordinates": [
        467.41015625,
        328.3984375
      ]
    },
    {
      "selector": ".ios-button",
      "type": "button",
      "text": "Assets",
      "attributes": {},
      "isClickable": true,
      "isVisible": true,
      "coordinates": [
        453.1484375,
        366.3984375
      ]
    },
    {
      "selector": ".ios-button",
      "type": "button",
      "text": "AIP Commander",
      "attributes": {},
      "isClickable": true,
      "isVisible": true,
      "coordinates": [
        486.234375,
        404.3984375
      ]
    },
    {
      "selector": ".zones-overview",
      "type": "div",
      "text": "Zone AIMMEDIATETotal Buildings:150Population:1500Evacuated (120)In Progress (20)Refused (5)No Contact (3)Unchecked (2)Est. Completion: 5:35:07 PM2 units assignedZone BWARNINGTotal Buildings:75Population:2200Evacuated (60)In Progress (10)Refused (2)No Contact (2)Unchecked (1)Est. Completion: 7:35:07 PM1 units assignedZone CSTANDBYTotal Buildings:50Population:800Evacuated (40)In Progress (5)Refused (1)No Contact (1)Unchecked (1)Est. Completion: 9:35:07 PM1 units assigned",
      "attributes": {},
      "isClickable": false,
      "isVisible": true,
      "coordinates": [
        960,
        691.3984375
      ]
    },
    {
      "selector": ".zones-grid",
      "type": "div",
      "text": "Zone AIMMEDIATETotal Buildings:150Population:1500Evacuated (120)In Progress (20)Refused (5)No Contact (3)Unchecked (2)Est. Completion: 5:35:07 PM2 units assignedZone BWARNINGTotal Buildings:75Population:2200Evacuated (60)In Progress (10)Refused (2)No Contact (2)Unchecked (1)Est. Completion: 7:35:07 PM1 units assignedZone CSTANDBYTotal Buildings:50Population:800Evacuated (40)In Progress (5)Refused (1)No Contact (1)Unchecked (1)Est. Completion: 9:35:07 PM1 units assigned",
      "attributes": {},
      "isClickable": false,
      "isVisible": true,
      "coordinates": [
        960,
        691.3984375
      ]
    },
    {
      "selector": ".zone-card",
      "type": "div",
      "text": "Zone AIMMEDIATETotal Buildings:150Population:1500Evacuated (120)In Progress (20)Refused (5)No Contact (3)Unchecked (2)Est. Completion: 5:35:07 PM2 units assigned",
      "attributes": {},
      "isClickable": false,
      "isVisible": true,
      "coordinates": [
        687,
        562.8984375
      ]
    },
    {
      "selector": ".zone-header",
      "type": "div",
      "text": "Zone AIMMEDIATE",
      "attributes": {},
      "isClickable": false,
      "isVisible": true,
      "coordinates": [
        687,
        478.1484375
      ]
    },
    {
      "selector": ".priority-badge",
      "type": "span",
      "text": "IMMEDIATE",
      "attributes": {},
      "isClickable": false,
      "isVisible": true,
      "coordinates": [
        889.42578125,
        478.1484375
      ]
    },
    {
      "selector": ".zone-stats",
      "type": "div",
      "text": "Total Buildings:150Population:1500",
      "attributes": {},
      "isClickable": false,
      "isVisible": true,
      "coordinates": [
        687,
        524.1484375
      ]
    },
    {
      "selector": ".stat",
      "type": "div",
      "text": "Total Buildings:150",
      "attributes": {},
      "isClickable": false,
      "isVisible": true,
      "coordinates": [
        562.25,
        524.1484375
      ]
    },
    {
      "selector": ".label",
      "type": "span",
      "text": "Total Buildings:",
      "attributes": {},
      "isClickable": false,
      "isVisible": true,
      "coordinates": [
        562.25,
        510.8984375
      ]
    },
    {
      "selector": ".value",
      "type": "span",
      "text": "150",
      "attributes": {},
      "isClickable": false,
      "isVisible": true,
      "coordinates": [
        562.25,
        533.6484375
      ]
    },
    {
      "selector": ".stat",
      "type": "div",
      "text": "Population:1500",
      "attributes": {},
      "isClickable": false,
      "isVisible": true,
      "coordinates": [
        811.75,
        524.1484375
      ]
    },
    {
      "selector": ".label",
      "type": "span",
      "text": "Population:",
      "attributes": {},
      "isClickable": false,
      "isVisible": true,
      "coordinates": [
        811.75,
        510.8984375
      ]
    },
    {
      "selector": ".value",
      "type": "span",
      "text": "1500",
      "attributes": {},
      "isClickable": false,
      "isVisible": true,
      "coordinates": [
        811.75,
        533.6484375
      ]
    },
    {
      "selector": ".progress-section",
      "type": "div",
      "text": "Evacuated (120)In Progress (20)Refused (5)No Contact (3)Unchecked (2)",
      "attributes": {},
      "isClickable": false,
      "isVisible": true,
      "coordinates": [
        687,
        586.3984375
      ]
    },
    {
      "selector": ".progress-bar",
      "type": "div",
      "attributes": {},
      "isClickable": false,
      "isVisible": true,
      "coordinates": [
        687,
        566.3984375
      ]
    },
    {
      "selector": ".progress-segment",
      "type": "div",
      "attributes": {
        "title": "80.0% Evacuated"
      },
      "isClickable": false,
      "isVisible": true,
      "coordinates": [
        638.59765625,
        566.3984375
      ]
    },
    {
      "selector": ".progress-segment",
      "type": "div",
      "attributes": {
        "title": "13.3% In Progress"
      },
      "isClickable": false,
      "isVisible": true,
      "coordinates": [
        864.4609375,
        566.3984375
      ]
    },
    {
      "selector": ".progress-segment",
      "type": "div",
      "attributes": {
        "title": "3.3% Refused"
      },
      "isClickable": false,
      "isVisible": true,
      "coordinates": [
        904.79296875,
        566.3984375
      ]
    },
    {
      "selector": ".progress-segment",
      "type": "div",
      "attributes": {
        "title": "2.0% No Contact"
      },
      "isClickable": false,
      "isVisible": true,
      "coordinates": [
        917.69921875,
        566.3984375
      ]
    },
    {
      "selector": ".progress-segment",
      "type": "div",
      "attributes": {
        "title": "1.3% Unchecked"
      },
      "isClickable": false,
      "isVisible": true,
      "coordinates": [
        925.765625,
        566.3984375
      ]
    },
    {
      "selector": ".progress-legend",
      "type": "div",
      "text": "Evacuated (120)In Progress (20)Refused (5)No Contact (3)Unchecked (2)",
      "attributes": {},
      "isClickable": false,
      "isVisible": true,
      "coordinates": [
        687,
        590.3984375
      ]
    },
    {
      "selector": ".legend-item",
      "type": "div",
      "text": "Evacuated (120)",
      "attributes": {},
      "isClickable": false,
      "isVisible": true,
      "coordinates": [
        523,
        579.3984375
      ]
    },
    {
      "selector": ".legend-color",
      "type": "span",
      "attributes": {},
      "isClickable": false,
      "isVisible": true,
      "coordinates": [
        451,
        579.3984375
      ]
    },
    {
      "selector": ".legend-item",
      "type": "div",
      "text": "In Progress (20)",
      "attributes": {},
      "isClickable": false,
      "isVisible": true,
      "coordinates": [
        687,
        579.3984375
      ]
    },
    {
      "selector": ".legend-color",
      "type": "span",
      "attributes": {},
      "isClickable": false,
      "isVisible": true,
      "coordinates": [
        615,
        579.3984375
      ]
    },
    {
      "selector": ".legend-item",
      "type": "div",
      "text": "Refused (5)",
      "attributes": {},
      "isClickable": false,
      "isVisible": true,
      "coordinates": [
        851,
        579.3984375
      ]
    },
    {
      "selector": ".legend-color",
      "type": "span",
      "attributes": {},
      "isClickable": false,
      "isVisible": true,
      "coordinates": [
        779,
        579.3984375
      ]
    },
    {
      "selector": ".legend-item",
      "type": "div",
      "text": "No Contact (3)",
      "attributes": {},
      "isClickable": false,
      "isVisible": true,
      "coordinates": [
        523,
        601.3984375
      ]
    },
    {
      "selector": ".legend-color",
      "type": "span",
      "attributes": {},
      "isClickable": false,
      "isVisible": true,
      "coordinates": [
        451,
        601.3984375
      ]
    },
    {
      "selector": ".legend-item",
      "type": "div",
      "text": "Unchecked (2)",
      "attributes": {},
      "isClickable": false,
      "isVisible": true,
      "coordinates": [
        687,
        601.3984375
      ]
    },
    {
      "selector": ".legend-color",
      "type": "span",
      "attributes": {},
      "isClickable": false,
      "isVisible": true,
      "coordinates": [
        615,
        601.3984375
      ]
    },
    {
      "selector": ".zone-footer",
      "type": "div",
      "text": "Est. Completion: 5:35:07 PM2 units assigned",
      "attributes": {},
      "isClickable": false,
      "isVisible": true,
      "coordinates": [
        687,
        643.3984375
      ]
    },
    {
      "selector": ".completion-estimate",
      "type": "span",
      "text": "Est. Completion: 5:35:07 PM",
      "attributes": {},
      "isClickable": false,
      "isVisible": true,
      "coordinates": [
        525.71484375,
        651.3984375
      ]
    },
    {
      "selector": ".assigned-units",
      "type": "span",
      "text": "2 units assigned",
      "attributes": {},
      "isClickable": false,
      "isVisible": true,
      "coordinates": [
        882.96875,
        651.3984375
      ]
    },
    {
      "selector": ".zone-card",
      "type": "div",
      "text": "Zone BWARNINGTotal Buildings:75Population:2200Evacuated (60)In Progress (10)Refused (2)No Contact (2)Unchecked (1)Est. Completion: 7:35:07 PM1 units assigned",
      "attributes": {},
      "isClickable": false,
      "isVisible": true,
      "coordinates": [
        1233,
        564.8984375
      ]
    },
    {
      "selector": ".zone-header",
      "type": "div",
      "text": "Zone BWARNING",
      "attributes": {},
      "isClickable": false,
      "isVisible": true,
      "coordinates": [
        1233,
        480.1484375
      ]
    },
    {
      "selector": ".priority-badge",
      "type": "span",
      "text": "WARNING",
      "attributes": {},
      "isClickable": false,
      "isVisible": true,
      "coordinates": [
        1439.87890625,
        480.1484375
      ]
    },
    {
      "selector": ".zone-stats",
      "type": "div",
      "text": "Total Buildings:75Population:2200",
      "attributes": {},
      "isClickable": false,
      "isVisible": true,
      "coordinates": [
        1233,
        526.1484375
      ]
    },
    {
      "selector": ".stat",
      "type": "div",
      "text": "Total Buildings:75",
      "attributes": {},
      "isClickable": false,
      "isVisible": true,
      "coordinates": [
        1108.25,
        526.1484375
      ]
    },
    {
      "selector": ".label",
      "type": "span",
      "text": "Total Buildings:",
      "attributes": {},
      "isClickable": false,
      "isVisible": true,
      "coordinates": [
        1108.25,
        512.8984375
      ]
    },
    {
      "selector": ".value",
      "type": "span",
      "text": "75",
      "attributes": {},
      "isClickable": false,
      "isVisible": true,
      "coordinates": [
        1108.25,
        535.6484375
      ]
    },
    {
      "selector": ".stat",
      "type": "div",
      "text": "Population:2200",
      "attributes": {},
      "isClickable": false,
      "isVisible": true,
      "coordinates": [
        1357.75,
        526.1484375
      ]
    },
    {
      "selector": ".label",
      "type": "span",
      "text": "Population:",
      "attributes": {},
      "isClickable": false,
      "isVisible": true,
      "coordinates": [
        1357.75,
        512.8984375
      ]
    },
    {
      "selector": ".value",
      "type": "span",
      "text": "2200",
      "attributes": {},
      "isClickable": false,
      "isVisible": true,
      "coordinates": [
        1357.75,
        535.6484375
      ]
    },
    {
      "selector": ".progress-section",
      "type": "div",
      "text": "Evacuated (60)In Progress (10)Refused (2)No Contact (2)Unchecked (1)",
      "attributes": {},
      "isClickable": false,
      "isVisible": true,
      "coordinates": [
        1233,
        588.3984375
      ]
    },
    {
      "selector": ".progress-bar",
      "type": "div",
      "attributes": {},
      "isClickable": false,
      "isVisible": true,
      "coordinates": [
        1233,
        568.3984375
      ]
    },
    {
      "selector": ".progress-segment",
      "type": "div",
      "attributes": {
        "title": "80.0% Evacuated"
      },
      "isClickable": false,
      "isVisible": true,
      "coordinates": [
        1184.59765625,
        568.3984375
      ]
    },
    {
      "selector": ".progress-segment",
      "type": "div",
      "attributes": {
        "title": "13.3% In Progress"
      },
      "isClickable": false,
      "isVisible": true,
      "coordinates": [
        1410.4609375,
        568.3984375
      ]
    },
    {
      "selector": ".progress-segment",
      "type": "div",
      "attributes": {
        "title": "2.7% Refused"
      },
      "isClickable": false,
      "isVisible": true,
      "coordinates": [
        1449.1796875,
        568.3984375
      ]
    },
    {
      "selector": ".progress-segment",
      "type": "div",
      "attributes": {
        "title": "2.7% No Contact"
      },
      "isClickable": false,
      "isVisible": true,
      "coordinates": [
        1462.0859375,
        568.3984375
      ]
    },
    {
      "selector": ".progress-segment",
      "type": "div",
      "attributes": {
        "title": "1.3% Unchecked"
      },
      "isClickable": false,
      "isVisible": true,
      "coordinates": [
        1471.765625,
        568.3984375
      ]
    },
    {
      "selector": ".progress-legend",
      "type": "div",
      "text": "Evacuated (60)In Progress (10)Refused (2)No Contact (2)Unchecked (1)",
      "attributes": {},
      "isClickable": false,
      "isVisible": true,
      "coordinates": [
        1233,
        592.3984375
      ]
    },
    {
      "selector": ".legend-item",
      "type": "div",
      "text": "Evacuated (60)",
      "attributes": {},
      "isClickable": false,
      "isVisible": true,
      "coordinates": [
        1069,
        581.3984375
      ]
    },
    {
      "selector": ".legend-color",
      "type": "span",
      "attributes": {},
      "isClickable": false,
      "isVisible": true,
      "coordinates": [
        997,
        581.3984375
      ]
    },
    {
      "selector": ".legend-item",
      "type": "div",
      "text": "In Progress (10)",
      "attributes": {},
      "isClickable": false,
      "isVisible": true,
      "coordinates": [
        1233,
        581.3984375
      ]
    },
    {
      "selector": ".legend-color",
      "type": "span",
      "attributes": {},
      "isClickable": false,
      "isVisible": true,
      "coordinates": [
        1161,
        581.3984375
      ]
    },
    {
      "selector": ".legend-item",
      "type": "div",
      "text": "Refused (2)",
      "attributes": {},
      "isClickable": false,
      "isVisible": true,
      "coordinates": [
        1397,
        581.3984375
      ]
    },
    {
      "selector": ".legend-color",
      "type": "span",
      "attributes": {},
      "isClickable": false,
      "isVisible": true,
      "coordinates": [
        1325,
        581.3984375
      ]
    },
    {
      "selector": ".legend-item",
      "type": "div",
      "text": "No Contact (2)",
      "attributes": {},
      "isClickable": false,
      "isVisible": true,
      "coordinates": [
        1069,
        603.3984375
      ]
    },
    {
      "selector": ".legend-color",
      "type": "span",
      "attributes": {},
      "isClickable": false,
      "isVisible": true,
      "coordinates": [
        997,
        603.3984375
      ]
    },
    {
      "selector": ".legend-item",
      "type": "div",
      "text": "Unchecked (1)",
      "attributes": {},
      "isClickable": false,
      "isVisible": true,
      "coordinates": [
        1233,
        603.3984375
      ]
    },
    {
      "selector": ".legend-color",
      "type": "span",
      "attributes": {},
      "isClickable": false,
      "isVisible": true,
      "coordinates": [
        1161,
        603.3984375
      ]
    },
    {
      "selector": ".zone-footer",
      "type": "div",
      "text": "Est. Completion: 7:35:07 PM1 units assigned",
      "attributes": {},
      "isClickable": false,
      "isVisible": true,
      "coordinates": [
        1233,
        645.3984375
      ]
    },
    {
      "selector": ".completion-estimate",
      "type": "span",
      "text": "Est. Completion: 7:35:07 PM",
      "attributes": {},
      "isClickable": false,
      "isVisible": true,
      "coordinates": [
        1071.36328125,
        653.3984375
      ]
    },
    {
      "selector": ".assigned-units",
      "type": "span",
      "text": "1 units assigned",
      "attributes": {},
      "isClickable": false,
      "isVisible": true,
      "coordinates": [
        1429.8046875,
        653.3984375
      ]
    },
    {
      "selector": ".zone-card",
      "type": "div",
      "text": "Zone CSTANDBYTotal Buildings:50Population:800Evacuated (40)In Progress (5)Refused (1)No Contact (1)Unchecked (1)Est. Completion: 9:35:07 PM1 units assigned",
      "attributes": {},
      "isClickable": false,
      "isVisible": true,
      "coordinates": [
        687,
        817.8984375
      ]
    },
    {
      "selector": ".zone-header",
      "type": "div",
      "text": "Zone CSTANDBY",
      "attributes": {},
      "isClickable": false,
      "isVisible": true,
      "coordinates": [
        687,
        733.1484375
      ]
    },
    {
      "selector": ".priority-badge",
      "type": "span",
      "text": "STANDBY",
      "attributes": {},
      "isClickable": false,
      "isVisible": true,
      "coordinates": [
        894.390625,
        733.1484375
      ]
    },
    {
      "selector": ".zone-stats",
      "type": "div",
      "text": "Total Buildings:50Population:800",
      "attributes": {},
      "isClickable": false,
      "isVisible": true,
      "coordinates": [
        687,
        779.1484375
      ]
    },
    {
      "selector": ".stat",
      "type": "div",
      "text": "Total Buildings:50",
      "attributes": {},
      "isClickable": false,
      "isVisible": true,
      "coordinates": [
        562.25,
        779.1484375
      ]
    },
    {
      "selector": ".label",
      "type": "span",
      "text": "Total Buildings:",
      "attributes": {},
      "isClickable": false,
      "isVisible": true,
      "coordinates": [
        562.25,
        765.8984375
      ]
    },
    {
      "selector": ".value",
      "type": "span",
      "text": "50",
      "attributes": {},
      "isClickable": false,
      "isVisible": true,
      "coordinates": [
        562.25,
        788.6484375
      ]
    },
    {
      "selector": ".stat",
      "type": "div",
      "text": "Population:800",
      "attributes": {},
      "isClickable": false,
      "isVisible": true,
      "coordinates": [
        811.75,
        779.1484375
      ]
    },
    {
      "selector": ".label",
      "type": "span",
      "text": "Population:",
      "attributes": {},
      "isClickable": false,
      "isVisible": true,
      "coordinates": [
        811.75,
        765.8984375
      ]
    },
    {
      "selector": ".value",
      "type": "span",
      "text": "800",
      "attributes": {},
      "isClickable": false,
      "isVisible": true,
      "coordinates": [
        811.75,
        788.6484375
      ]
    },
    {
      "selector": ".progress-section",
      "type": "div",
      "text": "Evacuated (40)In Progress (5)Refused (1)No Contact (1)Unchecked (1)",
      "attributes": {},
      "isClickable": false,
      "isVisible": true,
      "coordinates": [
        687,
        841.3984375
      ]
    },
    {
      "selector": ".progress-bar",
      "type": "div",
      "attributes": {},
      "isClickable": false,
      "isVisible": true,
      "coordinates": [
        687,
        821.3984375
      ]
    },
    {
      "selector": ".progress-segment",
      "type": "div",
      "attributes": {
        "title": "80.0% Evacuated"
      },
      "isClickable": false,
      "isVisible": true,
      "coordinates": [
        638.59765625,
        821.3984375
      ]
    },
    {
      "selector": ".progress-segment",
      "type": "div",
      "attributes": {
        "title": "10.0% In Progress"
      },
      "isClickable": false,
      "isVisible": true,
      "coordinates": [
        856.39453125,
        821.3984375
      ]
    },
    {
      "selector": ".progress-segment",
      "type": "div",
      "attributes": {
        "title": "2.0% Refused"
      },
      "isClickable": false,
      "isVisible": true,
      "coordinates": [
        885.43359375,
        821.3984375
      ]
    },
    {
      "selector": ".progress-segment",
      "type": "div",
      "attributes": {
        "title": "2.0% No Contact"
      },
      "isClickable": false,
      "isVisible": true,
      "coordinates": [
        895.11328125,
        821.3984375
      ]
    },
    {
      "selector": ".progress-segment",
      "type": "div",
      "attributes": {
        "title": "2.0% Unchecked"
      },
      "isClickable": false,
      "isVisible": true,
      "coordinates": [
        904.79296875,
        821.3984375
      ]
    },
    {
      "selector": ".progress-legend",
      "type": "div",
      "text": "Evacuated (40)In Progress (5)Refused (1)No Contact (1)Unchecked (1)",
      "attributes": {},
      "isClickable": false,
      "isVisible": true,
      "coordinates": [
        687,
        845.3984375
      ]
    },
    {
      "selector": ".legend-item",
      "type": "div",
      "text": "Evacuated (40)",
      "attributes": {},
      "isClickable": false,
      "isVisible": true,
      "coordinates": [
        523,
        834.3984375
      ]
    },
    {
      "selector": ".legend-color",
      "type": "span",
      "attributes": {},
      "isClickable": false,
      "isVisible": true,
      "coordinates": [
        451,
        834.3984375
      ]
    },
    {
      "selector": ".legend-item",
      "type": "div",
      "text": "In Progress (5)",
      "attributes": {},
      "isClickable": false,
      "isVisible": true,
      "coordinates": [
        687,
        834.3984375
      ]
    },
    {
      "selector": ".legend-color",
      "type": "span",
      "attributes": {},
      "isClickable": false,
      "isVisible": true,
      "coordinates": [
        615,
        834.3984375
      ]
    },
    {
      "selector": ".legend-item",
      "type": "div",
      "text": "Refused (1)",
      "attributes": {},
      "isClickable": false,
      "isVisible": true,
      "coordinates": [
        851,
        834.3984375
      ]
    },
    {
      "selector": ".legend-color",
      "type": "span",
      "attributes": {},
      "isClickable": false,
      "isVisible": true,
      "coordinates": [
        779,
        834.3984375
      ]
    },
    {
      "selector": ".legend-item",
      "type": "div",
      "text": "No Contact (1)",
      "attributes": {},
      "isClickable": false,
      "isVisible": true,
      "coordinates": [
        523,
        856.3984375
      ]
    },
    {
      "selector": ".legend-color",
      "type": "span",
      "attributes": {},
      "isClickable": false,
      "isVisible": true,
      "coordinates": [
        451,
        856.3984375
      ]
    },
    {
      "selector": ".legend-item",
      "type": "div",
      "text": "Unchecked (1)",
      "attributes": {},
      "isClickable": false,
      "isVisible": true,
      "coordinates": [
        687,
        856.3984375
      ]
    },
    {
      "selector": ".legend-color",
      "type": "span",
      "attributes": {},
      "isClickable": false,
      "isVisible": true,
      "coordinates": [
        615,
        856.3984375
      ]
    },
    {
      "selector": ".zone-footer",
      "type": "div",
      "text": "Est. Completion: 9:35:07 PM1 units assigned",
      "attributes": {},
      "isClickable": false,
      "isVisible": true,
      "coordinates": [
        687,
        898.3984375
      ]
    },
    {
      "selector": ".completion-estimate",
      "type": "span",
      "text": "Est. Completion: 9:35:07 PM",
      "attributes": {},
      "isClickable": false,
      "isVisible": true,
      "coordinates": [
        525.828125,
        906.3984375
      ]
    },
    {
      "selector": ".assigned-units",
      "type": "span",
      "text": "1 units assigned",
      "attributes": {},
      "isClickable": false,
      "isVisible": true,
      "coordinates": [
        883.8046875,
        906.3984375
      ]
    }
  ],
  "timestamp": 1755373440391,
  "url": "http://localhost:3000/",
  "exportInfo": {
    "timestamp": "2025-08-16T19:44:01.031Z",
    "totalComponents": 115,
    "clickableComponents": 10,
    "visibleComponents": 115,
    "componentTypes": [
      "button",
      "div",
      "h1",
      "p",
      "span"
    ],
    "selectors": [
      "button",
      "button",
      ".ios-button",
      ".ios-button",
      ".ios-button",
      ".ios-button",
      "#root",
      ".evacuation-dashboard",
      ".ios-card",
      ".ios-container",
      ".ios-flex-between",
      ".ios-headline",
      ".ios-caption",
      ".ios-card",
      ".ios-container",
      ".ios-flex",
      ".ios-button",
      ".ios-button",
      ".ios-button",
      ".ios-button",
      ".zones-overview",
      ".zones-grid",
      ".zone-card",
      ".zone-header",
      ".priority-badge",
      ".zone-stats",
      ".stat",
      ".label",
      ".value",
      ".stat",
      ".label",
      ".value",
      ".progress-section",
      ".progress-bar",
      ".progress-segment",
      ".progress-segment",
      ".progress-segment",
      ".progress-segment",
      ".progress-segment",
      ".progress-legend",
      ".legend-item",
      ".legend-color",
      ".legend-item",
      ".legend-color",
      ".legend-item",
      ".legend-color",
      ".legend-item",
      ".legend-color",
      ".legend-item",
      ".legend-color",
      ".zone-footer",
      ".completion-estimate",
      ".assigned-units",
      ".zone-card",
      ".zone-header",
      ".priority-badge",
      ".zone-stats",
      ".stat",
      ".label",
      ".value",
      ".stat",
      ".label",
      ".value",
      ".progress-section",
      ".progress-bar",
      ".progress-segment",
      ".progress-segment",
      ".progress-segment",
      ".progress-segment",
      ".progress-segment",
      ".progress-legend",
      ".legend-item",
      ".legend-color",
      ".legend-item",
      ".legend-color",
      ".legend-item",
      ".legend-color",
      ".legend-item",
      ".legend-color",
      ".legend-item",
      ".legend-color",
      ".zone-footer",
      ".completion-estimate",
      ".assigned-units",
      ".zone-card",
      ".zone-header",
      ".priority-badge",
      ".zone-stats",
      ".stat",
      ".label",
      ".value",
      ".stat",
      ".label",
      ".value",
      ".progress-section",
      ".progress-bar",
      ".progress-segment",
      ".progress-segment",
      ".progress-segment",
      ".progress-segment",
      ".progress-segment",
      ".progress-legend",
      ".legend-item",
      ".legend-color",
      ".legend-item",
      ".legend-color",
      ".legend-item",
      ".legend-color",
      ".legend-item",
      ".legend-color",
      ".legend-item",
      ".legend-color",
      ".zone-footer",
      ".completion-estimate",
      ".assigned-units"
    ]
  }
}